fibonacci/__init__.py
fibonacci/main.py
quiz_publish-0.0.1.dist-info/METADATA
quiz_publish-0.0.1.dist-info/WHEEL
quiz_publish-0.0.1.dist-info/license.txt
quiz_publish-0.0.1.dist-info/top_level.txt
quiz_publish-0.0.1.dist-info/RECORD
