Metadata-Version: 2.1
Name: quiz-publish
Version: 0.0.1
Summary: Fibonacci Series
Author: Lasha
Author-email: lasha.alievi.1@btu.edu.ge
Classifier: Programming Language :: Python :: 3
Classifier: License :: OSI Approved :: MIT License
Classifier: Operating System :: OS Independent
Requires-Python: >=3.6
License-File: license.txt
